bm_cli/__init__.py
bm_cli/cli.py
bm_cli/cli_utils.py
bm_cli/presets.py
bm_cli-0.1.2.dist-info/LICENSE
bm_cli-0.1.2.dist-info/METADATA
bm_cli-0.1.2.dist-info/WHEEL
bm_cli-0.1.2.dist-info/entry_points.txt
bm_cli-0.1.2.dist-info/top_level.txt
bm_cli-0.1.2.dist-info/RECORD
