Metadata-Version: 2.1
Name: bm-cli
Version: 0.1.2
Summary: Command line interface for boring man servers
Home-page: https://github.com/coyote963/bm-server-tools/
Author: coyote963
Author-email: coyoteandbird@gmail.com
License: UNKNOWN
Project-URL: Bug Tracker, https://github.com/coyote963/bm-server-tools/issues
Platform: UNKNOWN
Classifier: Programming Language :: Python :: 3
Classifier: License :: OSI Approved :: MIT License
Classifier: Operating System :: OS Independent
Requires-Python: >=3.6
License-File: LICENSE
Requires-Dist: certifi
Requires-Dist: charset-normalizer
Requires-Dist: docker
Requires-Dist: fire
Requires-Dist: idna
Requires-Dist: requests
Requires-Dist: six
Requires-Dist: tabulate
Requires-Dist: termcolor
Requires-Dist: toml
Requires-Dist: urllib3
Requires-Dist: websocket-client
